py_thumbnailer/__init__.py
py_thumbnailer/cli.py
py_thumbnailer/exceptions.py
py_thumbnailer/sh_utils.py
py_thumbnailer/thumbnail.py
py_thumbnailer/thumbnailers.py
py_thumbnailer-0.2.2.dist-info/DESCRIPTION.rst
py_thumbnailer-0.2.2.dist-info/METADATA
py_thumbnailer-0.2.2.dist-info/RECORD
py_thumbnailer-0.2.2.dist-info/WHEEL
py_thumbnailer-0.2.2.dist-info/entry_points.txt
py_thumbnailer-0.2.2.dist-info/metadata.json
py_thumbnailer-0.2.2.dist-info/top_level.txt
