Metadata-Version: 2.0
Name: py-thumbnailer
Version: 0.2.2
Summary: Documents Thumbnailer library
Home-page: https://github.com/razortheory/py_thumbnailer
Author: Roman Karpovich
Author-email: fpm.th13f@gmail.com
License: BSD
Platform: UNKNOWN
Classifier: Development Status :: 4 - Beta
Classifier: Intended Audience :: Developers
Classifier: Environment :: Console
Classifier: Environment :: Plugins
Classifier: License :: OSI Approved :: BSD License
Classifier: Operating System :: Unix
Classifier: Programming Language :: Python
Classifier: Programming Language :: Python :: 2
Classifier: Programming Language :: Python :: 2.6
Classifier: Programming Language :: Python :: 2.7
Requires-Dist: pillow
